rv32.vhd
library ieee;
use ieee.std_logic_1164.all;
use ieee.numeric_std.all;
use ieee.std_logic_unsigned.all;


entity RV32 is
  port (
    clk_i : in std_logic; -- Clock input
    rst_i : in std_logic; -- Active-high reset input
    instr_addr_o : out std_logic_vector(31 downto 0); -- 32-bit instruction address
    instr_data_i : in std_logic_vector(31 downto 0); -- 32-bit instruction data

    mem_we_o : out std_logic; -- Active-high memory write strobe
    mem_addr_o : out std_logic_vector(31 downto 0); -- 32-bit memory address 
    mem_data_i : in std_logic_vector(31 downto 0); -- 32-bit read memory data 
    mem_data_o : out std_logic_vector(31 downto 0) -- 32-bit write memory data
  );
  end;

architecture core of RV32 is
  function ToInt(v : std_logic_vector) return integer is
  begin
      return to_integer(unsigned(v));
  end function;

  signal instr_addr_buf : std_logic_vector(31 downto 0) := X"00000000";
  signal reg_deb : std_logic_vector(31 downto 0) := X"00000000";
  -- signal reg_x1 : std_logic_vector(31 downto 0);
  -- signal reg_x2 : std_logic_vector(31 downto 0);
  -- signal reg_x3 : std_logic_vector(31 downto 0);
  type registr_type is array (0 to 3) of std_logic_vector(31 downto 0);
  signal rex_x : registr_type :=(
    0 => X"00000000",
    1 => X"00000000",
    2 => X"00000008",
    3 => X"00000003"
  );
  signal debug : integer := 0;

begin
  -- process(rst_i)
  -- begin
  --   instr_addr_o <= X"00000000";
  -- end process;

  process(clk_i)
  begin
    if instr_data_i(1 downto 0) = "11" then -- if it is a command
      case instr_data_i(6 downto 2) is
        when "00100" => -- I-type
          case instr_data_i(14 downto 12) is
            when "000" => -- addi
              reg_deb <=
                rex_x(ToInt(instr_data_i(19 downto 15)))
                + instr_data_i(31 downto 20);
              rex_x(ToInt(instr_data_i(11 downto 7))) <=
                rex_x(ToInt(instr_data_i(19 downto 15)))
                + instr_data_i(31 downto 20);
            when "111" => -- andi
              -- rex_x(ToInt(instr_data_i(11 downto 7))) <=
              --   rex_x(ToInt(instr_data_i(19 downto 15))) and 
              --   instr_data_i(31 downto 20);
              reg_deb <=
                rex_x(ToInt(instr_data_i(19 downto 15)))
                and instr_data_i(31 downto 20);
              -- rex_x(ToInt(instr_data_i(11 downto 7))) <= X"11111111";
              --  1000 0000 0000 0000 0000 0000 0000 0000
            when others =>
              null;
          end case;
        when "01000" => -- S-type, memory
        case instr_data_i(14 downto 12) is
          when "010" => -- sw
          when others =>
            null;
          end case;

        when "00000" => -- I-type
          case instr_data_i(14 downto 12) is
            when "010" => -- lw
            when others =>
              null;
            end case;
        when others =>
          null;
      end case; 
    end if;
    instr_addr_o <= instr_addr_buf;
    instr_addr_buf <= instr_addr_buf + 4;
    -- instr_addr_o <= instr_addr_o + 4;

  end process;
end core;

rv32_tb.vhd
--

library ieee;
    use ieee.std_logic_1164.all;
    use ieee.numeric_std.all;
    use ieee.std_logic_unsigned.all;

entity RV32_tb is
end entity;

architecture arch of RV32_tb is

component RV32 is
    port (
        clk_i           : in  std_logic;                        -- Clock input
        rst_i           : in  std_logic;                        -- Active-hight reset input ('1' brings CPU in reset state)
        
        instr_addr_o    : out std_logic_vector(31 downto 0);    -- 32-bit instruction address
        instr_data_i    : in  std_logic_vector(31 downto 0);    -- 32-bit instruction data
        
        mem_we_o        : out std_logic;                        -- Active-high memory write strobe ('1' performs mem_data_o write to memory at address mem_addr_o)
        mem_addr_o      : out std_logic_vector(31 downto 0);    -- 32-bit memory address
        mem_data_i      : in  std_logic_vector(31 downto 0);    -- 32-bit read memory data
        mem_data_o      : out std_logic_vector(31 downto 0)     -- 32-bit write memory data
    );
end component;    
    
signal clk             : std_logic := '0';
signal rst             : std_logic := '1';
signal instr_addr      : std_logic_vector(31 downto 0);    -- 32-bit instruction address
signal instr_data      : std_logic_vector(31 downto 0);    -- 32-bit instruction data
signal mem_we          : std_logic;                        -- Active-high memory write strobe ('1' performs mem_data write to memory at address mem_addr_o)
signal mem_addr        : std_logic_vector(31 downto 0);    -- 32-bit memory address
signal mem_data_in     : std_logic_vector(31 downto 0);    -- 32-bit read memory data
signal mem_data_out    : std_logic_vector(31 downto 0);

constant MEMORY_SIZE    : integer := 32;
constant CLK_PERIOD     : time := 10 ns;

constant SIM_STOP_PC    : std_logic_vector(31 downto 0) := X"00000018";     -- decimal 24
constant MEM_CHECK_ADDR : integer                       := 16#40#;          -- decimal 64
constant EXPECTED_RESULT: std_logic_vector(31 downto 0) := X"00000031";     -- decimal 49

type memory_type is array (0 to MEMORY_SIZE-1) of std_logic_vector(31 downto 0);

function ToInt(v : std_logic_vector) return integer is
begin
    return to_integer(unsigned(v));
end function;

signal memory : memory_type := (
    X"04002083",    -- lw   x1, 64(x0)
    X"07b08113",    -- addi x2, x1, 123
    X"03310193",    -- addi x3, x2, 51
    X"03f1f193",    -- andi x3, x3, 63
    X"04302023",    -- sw   x3, 64(x0)
    X"00000013",    -- addi x0, x0, 0
    X"00000000",    -- <<execution will end here, PC=24 (hex 18)>>
    X"00000000",
    X"00000000",
    X"00000000",
    X"00000000",
    X"00000000",
    X"00000000",
    X"00000000",
    X"00000000",
    X"00000000",
    X"00000003",    -- <<address 64 (hex 40) for data>>
    X"00000000",
    X"00000000",
    X"00000000",
    X"00000000",
    X"00000000",
    X"00000000",
    X"00000000",
    X"00000000",
    X"00000000",
    X"00000000",
    X"00000000",
    X"00000000",
    X"00000000",
    X"00000000",
    X"00000000"
);

begin

-- Unit under test instance
cpu : RV32
    port map (
        clk_i           => clk,
        rst_i           => rst,
        
        instr_addr_o    => instr_addr,
        instr_data_i    => instr_data,
        
        mem_we_o        => mem_we,         
        mem_addr_o      => mem_addr,
        mem_data_i      => mem_data_in,
        mem_data_o      => mem_data_out
    );

-- Clock and reset generation
clk <= not clk after CLK_PERIOD/2;
rst <= '0' after CLK_PERIOD*10;

-- Read and write data from memory bus
DATA_MEM : process(rst, mem_we, mem_addr, mem_data_out)
begin
    if rst = '0' then
        assert mem_addr < MEMORY_SIZE*4 report "Data address is to large or undefined!" severity failure;
        
        mem_data_in <= memory(ToInt(mem_addr)/4);
        
        if (mem_we = '1') then
            memory(ToInt(mem_addr)/4) <= mem_data_out;
        end if;
    end if;
end process;


process(rst, instr_addr)
begin
    -- Read data for instruction bus
    instr_data <= memory(ToInt(instr_addr)/4);

    if rst = '0' then
        -- Check simulation stop condition
        assert instr_addr < MEMORY_SIZE*4 report "Instruction address is to large or undefined!" severity failure;
        
        if instr_addr = SIM_STOP_PC then
            if memory(MEM_CHECK_ADDR/4) = EXPECTED_RESULT then
                report "Stopping simulation: correct result found!" severity failure;
            else
                report "Stopping simulation: incorrect result, please fix your code and try again!" severity failure;
            end if;
        end if;
    end if;
end process;

end arch;

output.vcd
$date
  Wed Sep 15 23:59:58 2021
$end
$version
  GHDL v0
$end
$timescale
  1 fs
$end
$scope module standard $end
$upscope $end
$scope module textio $end
$upscope $end
$scope module std_logic_1164 $end
$upscope $end
$scope module numeric_std $end
$upscope $end
$scope module std_logic_arith $end
$upscope $end
$scope module std_logic_unsigned $end
$upscope $end
$scope module rv32_tb $end
$var reg 1 ! clk $end
$var reg 1 " rst $end
$var reg 32 # instr_addr[31:0] $end
$var reg 32 $ instr_data[31:0] $end
$var reg 1 % mem_we $end
$var reg 32 & mem_addr[31:0] $end
$var reg 32 ' mem_data_in[31:0] $end
$var reg 32 ( mem_data_out[31:0] $end
$comment memory is not handled $end
$scope module cpu $end
$var reg 1 ) clk_i $end
$var reg 1 * rst_i $end
$var reg 32 + instr_addr_o[31:0] $end
$var reg 32 , instr_data_i[31:0] $end
$var reg 1 - mem_we_o $end
$var reg 32 . mem_addr_o[31:0] $end
$var reg 32 / mem_data_i[31:0] $end
$var reg 32 0 mem_data_o[31:0] $end
$var reg 32 1 instr_addr_buf[31:0] $end
$var reg 32 2 reg_deb[31:0] $end
$comment rex_x is not handled $end
$var integer 32 3 debug $end
$upscope $end
$upscope $end
$enddefinitions $end
#0
0!
1"
b00000000000000000000000000000000 #
b00000100000000000010000010000011 $
U%
bUUUUUUUUUUUUUUUUUUUUUUUUUUUUUUUU &
bUUUUUUUUUUUUUUUUUUUUUUUUUUUUUUUU '
bUUUUUUUUUUUUUUUUUUUUUUUUUUUUUUUU (
0)
1*
b00000000000000000000000000000000 +
b00000100000000000010000010000011 ,
U-
bUUUUUUUUUUUUUUUUUUUUUUUUUUUUUUUU .
bUUUUUUUUUUUUUUUUUUUUUUUUUUUUUUUU /
bUUUUUUUUUUUUUUUUUUUUUUUUUUUUUUUU 0
b00000000000000000000000000000100 1
b00000000000000000000000000000000 2
b0 3
#5000000
1!
b00000000000000000000000000000100 #
b00000111101100001000000100010011 $
1)
b00000000000000000000000000000100 +
b00000111101100001000000100010011 ,
b00000000000000000000000000001000 1
#10000000
0!
b00000000000000000000000000001000 #
b00000011001100010000000110010011 $
0)
b00000000000000000000000000001000 +
b00000011001100010000000110010011 ,
b00000000000000000000000000001100 1
b00000000000000000000000001111011 2
#15000000
1!
b00000000000000000000000000001100 #
b00000011111100011111000110010011 $
1)
b00000000000000000000000000001100 +
b00000011111100011111000110010011 ,
b00000000000000000000000000010000 1
b00000000000000000000000010101110 2
#20000000
0!
b00000000000000000000000000010000 #
b00000100001100000010000000100011 $
0)
b00000000000000000000000000010000 +
b00000100001100000010000000100011 ,
b00000000000000000000000000010100 1
#25000000
1!
b00000000000000000000000000010100 #
b00000000000000000000000000010011 $
1)
b00000000000000000000000000010100 +
b00000000000000000000000000010011 ,
b00000000000000000000000000011000 1
#30000000
0!
b00000000000000000000000000011000 #
b00000000000000000000000000000000 $
0)
b00000000000000000000000000011000 +
b00000000000000000000000000000000 ,
b00000000000000000000000000011100 1
b00000000000000000000000000000000 2
#35000000
1!
b00000000000000000000000000011100 #
1)
b00000000000000000000000000011100 +
b00000000000000000000000000100000 1
#40000000
0!
b00000000000000000000000000100000 #
0)
b00000000000000000000000000100000 +
b00000000000000000000000000100100 1
#45000000
1!
b00000000000000000000000000100100 #
1)
b00000000000000000000000000100100 +
b00000000000000000000000000101000 1
#50000000
0!
b00000000000000000000000000101000 #
0)
b00000000000000000000000000101000 +
b00000000000000000000000000101100 1
#55000000
1!
b00000000000000000000000000101100 #
1)
b00000000000000000000000000101100 +
b00000000000000000000000000110000 1
#60000000
0!
b00000000000000000000000000110000 #
0)
b00000000000000000000000000110000 +
b00000000000000000000000000110100 1
#65000000
1!
b00000000000000000000000000110100 #
1)
b00000000000000000000000000110100 +
b00000000000000000000000000111000 1
#70000000
0!
b00000000000000000000000000111000 #
0)
b00000000000000000000000000111000 +
b00000000000000000000000000111100 1
#75000000
1!
b00000000000000000000000000111100 #
1)
b00000000000000000000000000111100 +
b00000000000000000000000001000000 1
#80000000
0!
b00000000000000000000000001000000 #
b00000000000000000000000000000011 $
0)
b00000000000000000000000001000000 +
b00000000000000000000000000000011 ,
b00000000000000000000000001000100 1
#85000000
1!
b00000000000000000000000001000100 #
b00000000000000000000000000000000 $
1)
b00000000000000000000000001000100 +
b00000000000000000000000000000000 ,
b00000000000000000000000001001000 1
#90000000
0!
b00000000000000000000000001001000 #
0)
b00000000000000000000000001001000 +
b00000000000000000000000001001100 1
#95000000
1!
b00000000000000000000000001001100 #
1)
b00000000000000000000000001001100 +
b00000000000000000000000001010000 1
